setup.cfg
setup.py
pyccuweather/__init__.py
pyccuweather/connector.py
pyccuweather/errors.py
pyccuweather/froots.py
pyccuweather/livetest.py
pyccuweather/objects.py
pyccuweather/utils.py
pyccuweather.egg-info/PKG-INFO
pyccuweather.egg-info/SOURCES.txt
pyccuweather.egg-info/dependency_links.txt
pyccuweather.egg-info/requires.txt
pyccuweather.egg-info/top_level.txt